odoo_docker_launcher/__init__.py
odoo_docker_launcher/config.py
odoo_docker_launcher/constants.py
odoo_docker_launcher/db.py
odoo_docker_launcher/deploy.py
odoo_docker_launcher/env.py
odoo_docker_launcher/services/__init__.py
odoo_docker_launcher/services/containers.py
odoo_docker_launcher/services/custom_logger.py
odoo_docker_launcher/services/database_creator.py
odoo_docker_launcher/services/file_operations.py
odoo_docker_launcher/services/module_manager.py
odoo_docker_launcher/services/traefik.py
pymtech_docker_launcher-1.0.1.dist-info/METADATA
pymtech_docker_launcher-1.0.1.dist-info/WHEEL
pymtech_docker_launcher-1.0.1.dist-info/entry_points.txt
pymtech_docker_launcher-1.0.1.dist-info/RECORD
