Metadata-Version: 2.4
Name: pymtech-docker-launcher
Version: 1.0.1
Summary: Odoo deploy command line tool
Requires-Python: >=3.10.12
Requires-Dist: oci-cli>=3.68.0
Requires-Dist: playwright>=1.55.0
Requires-Dist: psutil>=7.1.0
Requires-Dist: python-dotenv>=1.1.1
Requires-Dist: requests>=2.32.5
Requires-Dist: typer>=0.20.0
